omada/__init__.py
omada/api_bindings.py
omada/function_interface_bindings.py
omada/omada.py
omada_api-0.1.3.dist-info/LICENSE
omada_api-0.1.3.dist-info/METADATA
omada_api-0.1.3.dist-info/WHEEL
omada_api-0.1.3.dist-info/RECORD
