Metadata-Version: 2.1
Name: omada-api
Version: 0.1.3
Summary: A simple Python wrapper for the TP-Link Omada Software Controller API
License: MIT
Keywords: tplink,omada,wrapper
Author: Ilja O
Author-email: vrghost@gmail.com
Requires-Python: >=3.8,<4.0
Classifier: Development Status :: 4 - Beta
Classifier: Intended Audience :: Developers
Classifier: License :: OSI Approved :: MIT License
Classifier: Operating System :: OS Independent
Classifier: Programming Language :: Python :: 3
Classifier: Programming Language :: Python :: 3.8
Classifier: Programming Language :: Python :: 3.9
Classifier: Programming Language :: Python :: 3.10
Classifier: Programming Language :: Python :: 3.11
Classifier: Programming Language :: Python :: 3.7
Classifier: Topic :: Software Development :: Libraries
Requires-Dist: pydantic (>=1.10.9,<2.0.0)
Requires-Dist: requests (>=2.31.0,<3.0.0)
Requires-Dist: yarl (>=1.9.2,<2.0.0)
Project-URL: Source, https://github.com/vrghost/omada-api
